{"title": "pandoc", "source": "gtfobins", "source_label": "GTFOBins", "path": "pandoc", "html": "<h1>pandoc</h1>\n<h2>File Read</h2>\n<pre><code class=\"language-bash\">pandoc -t plain /path/to/input-file</code></pre>\n<h2>File Write</h2>\n<pre><code class=\"language-bash\">echo DATA | pandoc -t plain -o /path/to/output-file</code></pre>\n<h2>Inherit</h2>\n<p>This allows to run Lua code (`...`).</p>\n<pre><code class=\"language-bash\">echo &#x27;...&#x27; &gt;/path/to/temp-file\npandoc -L /path/to/temp-file /dev/null</code></pre>", "excerpt": "pandoc File Read pandoc -t plain /path/to/input-file File Write echo DATA | pandoc -t plain -o /path/to/output-file Inherit This allows to run Lua code (`...`). echo &#x27;...&#x27; &gt;/path/to/temp-file pandoc -L /path/to/temp-file /dev/null", "tags": ["func:file-read", "func:file-write", "func:inherit", "ctx:sudo", "ctx:suid", "ctx:unprivileged"]}